cmem_plugin_semspect/__init__.py
cmem_plugin_semspect/api.py
cmem_plugin_semspect/logo.svg
cmem_plugin_semspect/task.py
cmem_plugin_semspect-0.7.0.dist-info/LICENSE
cmem_plugin_semspect-0.7.0.dist-info/METADATA
cmem_plugin_semspect-0.7.0.dist-info/WHEEL
cmem_plugin_semspect-0.7.0.dist-info/RECORD
