Metadata-Version: 2.1
Name: cmem-plugin-semspect
Version: 0.7.0
Summary: Update Knowledge Graphs for visualisation in derivo SemSpect RDF.
License: Apache-2.0
Keywords: eccenca Corporate Memory,plugin
Author: eccenca GmbH
Author-email: cmempy-developer@eccenca.com
Requires-Python: >=3.11,<4.0
Classifier: Development Status :: 4 - Beta
Classifier: Environment :: Plugins
Classifier: License :: OSI Approved :: Apache Software License
Classifier: Programming Language :: Python :: 3
Classifier: Programming Language :: Python :: 3.11
Classifier: Programming Language :: Python :: 3.12
Classifier: Topic :: Software Development :: Libraries :: Python Modules
Requires-Dist: cmem-plugin-base (>=4.5.0,<5.0.0)
Requires-Dist: pydantic (>=2.7.4,<3.0.0)
